guardionsdk/__init__.py
guardionsdk/exceptions.py
guardionsdk/guardionsdk.py
guardionsdk/langchain.py
guardionsdk/openai_agents.py
guardionsdk-0.1.0.dist-info/METADATA
guardionsdk-0.1.0.dist-info/WHEEL
guardionsdk-0.1.0.dist-info/RECORD
