Metadata-Version: 2.3
Name: guardionsdk
Version: 0.1.0
Summary: The Guardion AI SDK
Maintainer: Guardion.ai
Maintainer-email: opensource@guardion.ai
Requires-Python: >=3.11
Classifier: Programming Language :: Python :: 3
Classifier: Programming Language :: Python :: 3.11
Classifier: Programming Language :: Python :: 3.12
Classifier: Programming Language :: Python :: 3.13
Provides-Extra: langchain
Provides-Extra: openai-agents
Requires-Dist: httpx (>=0.28.1)
Requires-Dist: langchain (>=0.3.24) ; extra == "langchain"
Requires-Dist: langchain-community (>=0.3.23) ; extra == "langchain"
Requires-Dist: langchain-core (>=0.3.56) ; extra == "langchain"
Requires-Dist: langchain-openai (>=0.3.14) ; extra == "langchain"
Requires-Dist: openai-agents (>=0.0.13) ; extra == "openai-agents"
Requires-Dist: requests (>=2.32.3)
